dbt_copilot_python/__init__.py
dbt_copilot_python/celery_health_check/__init__.py
dbt_copilot_python/celery_health_check/const.py
dbt_copilot_python/celery_health_check/healthcheck.py
dbt_copilot_python/celery_health_check/heartbeat.py
dbt_copilot_python/database.py
dbt_copilot_python/network.py
dbt_copilot_python/utility.py
dbt_copilot_python-2.0.0.dist-info/METADATA
dbt_copilot_python-2.0.0.dist-info/WHEEL
dbt_copilot_python-2.0.0.dist-info/licenses/LICENSE
dbt_copilot_python-2.0.0.dist-info/RECORD
