Metadata-Version: 2.4
Name: dbt-copilot-python
Version: 2.0.0
Summary: Helper functions to run Django and Flask applications in AWS Copilot/ECS.
License-File: LICENSE
Author: Department for Business and Trade Platform Team
Author-email: sre-team@digital.trade.gov.uk
Requires-Python: >=3.9,<4.0
Classifier: Programming Language :: Python :: 3
Classifier: Programming Language :: Python :: 3.9
Classifier: Programming Language :: Python :: 3.10
Classifier: Programming Language :: Python :: 3.11
Classifier: Programming Language :: Python :: 3.12
Classifier: Programming Language :: Python :: 3.13
Classifier: Programming Language :: Python :: 3.14
Provides-Extra: celery
Requires-Dist: celery (>=5.0) ; extra == "celery"
Requires-Dist: requests (>=2.32.3,<3.0.0)
